pylangs/__init__.py
pylangs/_json.py
pylangs/_lang.py
pylangs/_langs.py
pylangs-0.0.2.dist-info/LICENSE
pylangs-0.0.2.dist-info/METADATA
pylangs-0.0.2.dist-info/WHEEL
pylangs-0.0.2.dist-info/top_level.txt
pylangs-0.0.2.dist-info/RECORD
