Metadata-Version: 2.1
Name: pylangs
Version: 0.0.2
Summary: A Python library designed to simplify the management of multiple languages in projects that need to support internationalization.
Author-email: ZAID <me@zaid.pro>
Requires-Python: >=3.8
License-File: LICENSE
